{"projectInfo":{"projectName":"Project_with_2_text_boxes_and_overflow","templateID":""},"documentSettings":{"pageWidth":8.5,"pageHeight":11},"pages":[{"pageIndex":1,"assets":[{"assetType":"Article","position":{"startX":4.28125,"startY":5.53125},"size":{"width":4,"height":4.5},"content":{"textBody":"ing in statistics and data science."},"columns":1,"gutterSize":0.1667,"margins":{"top":0,"left":0,"bottom":0,"right":0},"textStyle":{"fontFamily":"Arial","fontSize":12,"bold":false,"italic":false,"underline":false,"color":"#000000","autoFit":false}},{"assetType":"Article","position":{"startX":0.125,"startY":0.125},"size":{"width":4.0625,"height":5.3125},"content":{"textBody":"caught a performance by Olivia Hughes. With her close friend Sam Wood, Olivia sang all through high school and college, sharing her love of music with the community.\n\nAt school, the Hughes kids carved their own unique paths. Olivia attended Canyon Creek Elementary, then pursued art through Richardson’s magnet program, eventually earning a Fine Art degree from USC. Today, she’s building a career in animation—already working on two music videos and contributing to Apple TV’s Shape Island. Most recently, she created a whimsical photo op installation for the 2024 Wildflower! Festival.\n\nMeanwhile, Owen’s journey took him in another direction. A talented musician in the JJ Pearce Mighty Mustang Band, he eventually followed his interest in communication and numbers. Now in his third year at UT Austin, Owen is majoring in advertising and minoring in statistics and data science.\n\nMeanwhile, Owen’s journey took him in another direction. A talented musician in the JJ Pearce Mighty Mustang Band, he eventually followed his interest in communication and numbers. Now in his third year at UT Austin, Owen is majoring in advertising and minor"},"columns":1,"gutterSize":0.1667,"margins":{"top":0,"left":0,"bottom":0,"right":0},"textStyle":{"fontFamily":"Arial","fontSize":12,"bold":false,"italic":false,"underline":false,"color":"#000000","autoFit":false}}]},{"pageIndex":2,"assets":[{"assetType":"Article","position":{"startX":0.125,"startY":0.125},"size":{"width":8.25,"height":10.75},"content":{"textBody":"caught a performance by Olivia Hughes. With her close friend Sam Wood, Olivia sang all through high school and college, sharing her love of music with the community.\n\nAt school, the Hughes kids carved their own unique paths. Olivia attended Canyon Creek Elementary, then pursued art through Richardson’s magnet program, eventually earning a Fine Art degree from USC. Today, she’s building a career in animation—already working on two music videos and contributing to Apple TV’s Shape Island. Most recently, she created a whimsical photo op installation for the 2024 Wildflower! Festival.\n\nMeanwhile, Owen’s journey took him in another direction. A talented musician in the JJ Pearce Mighty Mustang Band, he eventually followed his interest in communication and numbers. Now in his third year at UT Austin, Owen is majoring in advertising and minoring in statistics and data science.\n\nMeanwhile, Owen’s journey took him in another direction. A talented musician in the JJ Pearce Mighty Mustang Band, he eventually followed his interest in communication and numbers. Now in his third year at UT Austin, Owen is majoring in advertising and minoring in statistics and data science."},"columns":1,"gutterSize":0.1667,"margins":{"top":0,"left":0,"bottom":0,"right":0},"textStyle":{"fontFamily":"Arial","fontSize":12,"bold":false,"italic":false,"underline":false,"color":"#000000","autoFit":false}}]}]}